tfv_get_tools/__init__.py
tfv_get_tools/_standard_attrs.py
tfv_get_tools/atmos.py
tfv_get_tools/ocean.py
tfv_get_tools/wave.py
tfv_get_tools/cli/_cli_base.py
tfv_get_tools/cli/atmos_cli.py
tfv_get_tools/cli/ocean_cli.py
tfv_get_tools/cli/tide_cli.py
tfv_get_tools/cli/wave_cli.py
tfv_get_tools/fvc/__init__.py
tfv_get_tools/fvc/_atmos.py
tfv_get_tools/fvc/_fvc.py
tfv_get_tools/fvc/_ocean.py
tfv_get_tools/fvc/_tide.py
tfv_get_tools/providers/__init__.py
tfv_get_tools/providers/_custom_conversions.py
tfv_get_tools/providers/_downloader.py
tfv_get_tools/providers/_merger.py
tfv_get_tools/providers/_utilities.py
tfv_get_tools/providers/atmos/barra2.py
tfv_get_tools/providers/atmos/cfsr.py
tfv_get_tools/providers/atmos/era5.py
tfv_get_tools/providers/atmos/era5_gcp.py
tfv_get_tools/providers/atmos/cfgs/barra2_c2.yaml
tfv_get_tools/providers/atmos/cfgs/barra2_r2.yaml
tfv_get_tools/providers/atmos/cfgs/barra2_re2.yaml
tfv_get_tools/providers/atmos/cfgs/cfsr.yaml
tfv_get_tools/providers/atmos/cfgs/era5.yaml
tfv_get_tools/providers/atmos/cfgs/era5_gcp.yaml
tfv_get_tools/providers/ocean/copernicus_ocean.py
tfv_get_tools/providers/ocean/hycom.py
tfv_get_tools/providers/ocean/cfgs/copernicus_blk.yaml
tfv_get_tools/providers/ocean/cfgs/copernicus_glo.yaml
tfv_get_tools/providers/ocean/cfgs/copernicus_nws.yaml
tfv_get_tools/providers/ocean/cfgs/hycom.yaml
tfv_get_tools/providers/wave/cawcr.py
tfv_get_tools/providers/wave/copernicus_wave.py
tfv_get_tools/providers/wave/era5.py
tfv_get_tools/providers/wave/era5_gcp.py
tfv_get_tools/providers/wave/cfgs/cawcr_aus_10m.yaml
tfv_get_tools/providers/wave/cfgs/cawcr_aus_4m.yaml
tfv_get_tools/providers/wave/cfgs/cawcr_glob_24m.yaml
tfv_get_tools/providers/wave/cfgs/cawcr_pac_10m.yaml
tfv_get_tools/providers/wave/cfgs/cawcr_pac_4m.yaml
tfv_get_tools/providers/wave/cfgs/copernicus_glo.yaml
tfv_get_tools/providers/wave/cfgs/copernicus_nws.yaml
tfv_get_tools/providers/wave/cfgs/era5.yaml
tfv_get_tools/providers/wave/cfgs/era5_gcp.yaml
tfv_get_tools-0.2.4.dist-info/licenses/LICENSE
tfv_get_tools-0.2.4.dist-info/METADATA
tfv_get_tools-0.2.4.dist-info/WHEEL
tfv_get_tools-0.2.4.dist-info/entry_points.txt
tfv_get_tools-0.2.4.dist-info/top_level.txt
tfv_get_tools-0.2.4.dist-info/RECORD
