Metadata-Version: 2.4
Name: tfv_get_tools
Version: 0.2.4
Summary: Tool for downloading and processing data for TUFLOW FV modelling
Author-email: Alex Waterhouse <alex.waterhouse@apac.bmt.org>, Mitchell Smith <mitchell.smith@apac.bmt.org>, TUFLOW Support <support@tuflow.com>
License: MIT
Project-URL: Homepage, https://gitlab.com/tuflow-user-group/tuflow-fv/data-pre-processing/tfv-get-tools
Project-URL: Repository, https://gitlab.com/tuflow-user-group/tuflow-fv/data-pre-processing/tfv-get-tools
Project-URL: Issues, https://gitlab.com/tuflow-user-group/tuflow-fv/data-pre-processing/tfv-get-tools/issues
Classifier: Development Status :: 3 - Alpha
Classifier: Intended Audience :: Science/Research
Classifier: License :: OSI Approved :: MIT License
Classifier: Programming Language :: Python :: 3
Classifier: Programming Language :: Python :: 3.9
Classifier: Programming Language :: Python :: 3.10
Classifier: Programming Language :: Python :: 3.11
Classifier: Programming Language :: Python :: 3.12
Classifier: Programming Language :: Python :: 3.13
Requires-Python: <3.14,>=3.9
License-File: LICENSE
Requires-Dist: netCDF4>=1.6.2
Requires-Dist: tqdm>=4.65.0
Requires-Dist: xarray>=2023.1.0
Requires-Dist: scipy>=1.10.0
Requires-Dist: pyproj>=3.5.0
Requires-Dist: siphon>=0.9
Requires-Dist: cdsapi>=0.7.0
Requires-Dist: copernicusmarine>=1.2.3
Requires-Dist: bottleneck>=1.3.5
Requires-Dist: pyTMD>=2.1.5
Requires-Dist: shapely>=2.0.6
Requires-Dist: geopandas>=1.0.1
Provides-Extra: dev
Requires-Dist: ipython>=8.6.0; extra == "dev"
Requires-Dist: notebook>=6.5.2; extra == "dev"
Requires-Dist: ipykernel>=6.17.1; extra == "dev"
Requires-Dist: dask>=2022.11.0; extra == "dev"
Requires-Dist: black>=22.12.0; extra == "dev"
Requires-Dist: matplotlib>=3.7.0; extra == "dev"
Requires-Dist: sphinx>=7.3.7; extra == "dev"
Requires-Dist: recommonmark>=0.7.1; extra == "dev"
Requires-Dist: sphinx-markdown-builder>=0.6.6; extra == "dev"
Requires-Dist: pyprojroot; extra == "dev"
Dynamic: license-file
